oracle/__init__.py
oracle/oci_logging_mcp_server/__init__.py
oracle/oci_logging_mcp_server/models.py
oracle/oci_logging_mcp_server/scripts.py
oracle/oci_logging_mcp_server/server.py
oracle/oci_logging_mcp_server/scripts/SEARCH_LOG.md
oracle/oci_logging_mcp_server/scripts/SEARCH_LOG_EVENT_TYPES.md
oracle/oci_logging_mcp_server/tests/test_logging_tools.py
oracle_oci_logging_mcp_server-1.2.0.dist-info/METADATA
oracle_oci_logging_mcp_server-1.2.0.dist-info/WHEEL
oracle_oci_logging_mcp_server-1.2.0.dist-info/entry_points.txt
oracle_oci_logging_mcp_server-1.2.0.dist-info/licenses/LICENSE.txt
oracle_oci_logging_mcp_server-1.2.0.dist-info/RECORD
